jupyter_pytest
